ya_music_rnd/__init__.py
ya_music_rnd-1.1.0.dist-info/LICENSE
ya_music_rnd-1.1.0.dist-info/METADATA
ya_music_rnd-1.1.0.dist-info/WHEEL
ya_music_rnd-1.1.0.dist-info/top_level.txt
ya_music_rnd-1.1.0.dist-info/RECORD
