Metadata-Version: 2.1
Name: ya-music-rnd
Version: 1.1.0
Summary: Поиск случайного исполнителя на сайте яндекс музыки
Home-page: https://github.com/Genzo4/yandex_rnd
Author: Genzo
Author-email: genzo@bk.ru
License: MIT
Project-URL: Bug Tracker, https://github.com/Genzo4/yandex_rnd/issues
Keywords: yandex,music,yandex_rnd,ya_music_rnd,ya
Classifier: Development Status :: 5 - Production/Stable
Classifier: Programming Language :: Python :: 3
Classifier: Programming Language :: Python :: 3.8
Classifier: Programming Language :: Python :: 3.9
Classifier: Programming Language :: Python :: 3.10
Classifier: License :: OSI Approved :: MIT License
Classifier: Operating System :: OS Independent
Classifier: Intended Audience :: Developers
Classifier: Intended Audience :: End Users/Desktop
Classifier: Natural Language :: English
Classifier: Natural Language :: Russian
Classifier: Topic :: Scientific/Engineering
Classifier: Topic :: Software Development
Classifier: Topic :: Software Development :: Libraries :: Python Modules
Requires-Python: >=3.8
License-File: LICENSE
Requires-Dist: urllib3
